LICENSE
MANIFEST.in
README.md
pyproject.toml
setup.cfg
setup.py
account/__init__.py
account/admin.py
account/apps.py
account/models.py
account/tests.py
account/urls.py
account/views.py
account/migrations/__init__.py
account/python/__init__.py
account/python/form.py
account/python/smtp.py
account/python/static_messages.py
account/static/accounts/css/accounts.css
account/static/commons/dummy
account/static/commons/img/favicon.ico
account/templates/account/base.html
account/templates/account/dummy.html
account/templates/account/register.html
account/templates/account/partial/_footer.html
account/templates/account/partial/_head.html
account/templates/components/messages.html
account/templates/components/partial/message_alert.html
account/templates/components/partial/message_icons.html
account/templates/registration/logged_out.html
account/templates/registration/login.html
account/templates/registration/password_change_form.html
account/templates/registration/password_reset_complete.html
account/templates/registration/password_reset_confirm.html
account/templates/registration/password_reset_done.html
account/templates/registration/password_reset_email.html
account/templates/registration/password_reset_form.html
jnunes_account.egg-info/PKG-INFO
jnunes_account.egg-info/SOURCES.txt
jnunes_account.egg-info/dependency_links.txt
jnunes_account.egg-info/requires.txt
jnunes_account.egg-info/top_level.txt